pdfsc/__init__.py
pdfsc/cli.py
pdfsc/code_to_pdf.py
pdfsc-2.0.8.dist-info/METADATA
pdfsc-2.0.8.dist-info/WHEEL
pdfsc-2.0.8.dist-info/entry_points.txt
pdfsc-2.0.8.dist-info/licenses/LICENSE
pdfsc-2.0.8.dist-info/RECORD
