Metadata-Version: 2.3
Name: pdfsc
Version: 2.0.8
Summary: A small example package
Project-URL: Homepage, https://github.com/utsmannn/code-to-pdf
Project-URL: Issues, https://github.com/utsmannn/code-to-pdf/issues
Author-email: Muhammad Utsman <utsmannn@gmail.com>
License-File: LICENSE
Classifier: License :: OSI Approved :: MIT License
Classifier: Operating System :: OS Independent
Classifier: Programming Language :: Python :: 3
Requires-Python: >=3.8
